baseball_Info/__init__.py
baseball_Info/player.py
baseball_Info/team.py
Baseball_Info-0.0.1.8.dist-info/METADATA
Baseball_Info-0.0.1.8.dist-info/WHEEL
Baseball_Info-0.0.1.8.dist-info/top_level.txt
Baseball_Info-0.0.1.8.dist-info/RECORD
