Metadata-Version: 2.1
Name: Baseball-Info
Version: 0.0.1.8
Summary: baseball API
Home-page: 
Author: basekk
Author-email: jino152637@gmail.com
License: MIT
Requires-Python: >=3.4
Requires-Dist: tabulate
